FlexableThreadPoolExecutor/__init__.py
FlexableThreadPoolExecutor/flexable_thread.py
flexable_thread-1.0.2.dist-info/LICENSE
flexable_thread-1.0.2.dist-info/METADATA
flexable_thread-1.0.2.dist-info/WHEEL
flexable_thread-1.0.2.dist-info/top_level.txt
flexable_thread-1.0.2.dist-info/RECORD
