Metadata-Version: 2.1
Name: flexable-thread
Version: 1.0.2
Summary: 弹性线程池
Home-page: https://github.com/AlitaIcon/flexable-thread
Author: alita
Author-email: 1906321518@qq.com
License: MIT
Project-URL: Documentation, https://github.com/AlitaIcon/flexable-thread
Classifier: Programming Language :: Python :: 3
Classifier: License :: OSI Approved :: MIT License
Classifier: Operating System :: OS Independent
Requires-Python: >=3.7
License-File: LICENSE
Requires-Dist: loguru (>=0.6.0)
Requires-Dist: apscheduler (>=3.9.1)
